upytimerobot/__init__.py
upytimerobot/colors.py
upytimerobot/config.py
upytimerobot/constants.py
upytimerobot-0.2.1.dist-info/DESCRIPTION.rst
upytimerobot-0.2.1.dist-info/METADATA
upytimerobot-0.2.1.dist-info/RECORD
upytimerobot-0.2.1.dist-info/WHEEL
upytimerobot-0.2.1.dist-info/metadata.json
upytimerobot-0.2.1.dist-info/top_level.txt
