Metadata-Version: 2.0
Name: upytimerobot
Version: 0.2.1
Summary: Python3 module to interact with UptimeRobot API.
Home-page: https://gitlab.com/fboaventura/upytimerobot
Author: Frederico Freire Boaventura
Author-email: frederico@boaventura.net
License: The MIT License
Keywords: Uptime robot,API,monitoring
Platform: OS Independent
Classifier: Programming Language :: Python :: 3
Classifier: License :: OSI Approved :: MIT License
Classifier: Operating System :: OS Independent
